magic_import.py
magic_import-0.2.3.dist-info/licenses/LICENSE
magic_import-0.2.3.dist-info/METADATA
magic_import-0.2.3.dist-info/WHEEL
magic_import-0.2.3.dist-info/top_level.txt
magic_import-0.2.3.dist-info/RECORD
