Metadata-Version: 2.4
Name: magic-import
Version: 0.2.3
Summary: Import python object from string and return the reference of the object. The object can be a class, instance, variable and anything else, and can be from class, instance, module, global/local environment.
Author: rRR0VrFP
Maintainer: rRR0VrFP
License: MIT
Keywords: magic-import
Classifier: Development Status :: 5 - Production/Stable
Classifier: Intended Audience :: Developers
Classifier: Topic :: Software Development :: Libraries :: Python Modules
Classifier: License :: OSI Approved :: MIT License
Classifier: Programming Language :: Python :: 3
Classifier: Programming Language :: Python :: 3 :: Only
Requires: dictop
License-File: LICENSE
Requires-Dist: dictop
Dynamic: author
Dynamic: classifier
Dynamic: description
Dynamic: description-content-type
Dynamic: keywords
Dynamic: license
Dynamic: license-file
Dynamic: maintainer
Dynamic: requires
Dynamic: requires-dist
Dynamic: summary
